pycpu_retro70z_id0000/__init__.py
pycpu_retro70z_id0000/control.py
tests/__init__.py
tests/test_pycpu_retro70z_id0000.py
PyCPU_RETRO70Z_ID0000-0.0.11.dist-info/LICENSE.md
PyCPU_RETRO70Z_ID0000-0.0.11.dist-info/METADATA
PyCPU_RETRO70Z_ID0000-0.0.11.dist-info/WHEEL
PyCPU_RETRO70Z_ID0000-0.0.11.dist-info/top_level.txt
PyCPU_RETRO70Z_ID0000-0.0.11.dist-info/RECORD
