Metadata-Version: 2.1
Name: PyCPU-RETRO70Z-ID0000
Version: 0.0.11
Summary: 'C' Implementation of RETROFORTH: 4MiB (1M) CELLs, STACK:256, v2020.10
Home-page: https://github.com/PyCPU/PyCPU_RETRO70Z_ID0000
Author: Scott McCallum (https github.com scott91e1) << Charles Childers (https github.com crcx)
Author-email: 262464@195387.com
License: UNKNOWN
Platform: UNKNOWN
Classifier: Programming Language :: Python :: 3
Classifier: License :: OSI Approved :: MIT License
Classifier: Operating System :: OS Independent
Requires-Python: >=3.6
